linksdk/__init__.py
linksdk/__main__.py
linksdk/__version__.py
linksdk/bridge.py
linksdk/consts.py
linksdk/controller.py
linksdk/discovery.py
linksdk/endpoint.py
linksdk/exceptions.py
linksdk/handler.py
linksdk/manufacturers.py
linksdk/py.typed
linksdk/wiim_device.py
linksdk-0.0.1a112.dist-info/licenses/LICENSE
wiim/__init__.py
wiim/__main__.py
wiim/__version__.py
wiim/bridge.py
wiim/consts.py
wiim/controller.py
wiim/discovery.py
wiim/endpoint.py
wiim/exceptions.py
wiim/handler.py
wiim/manufacturers.py
wiim/py.typed
wiim/wiim_device.py
linksdk-0.0.1a112.dist-info/METADATA
linksdk-0.0.1a112.dist-info/WHEEL
linksdk-0.0.1a112.dist-info/top_level.txt
linksdk-0.0.1a112.dist-info/RECORD
